<?xml version="1.0" encoding="UTF-8"?><mods:mods xmlns:mods="http://www.loc.gov/mods/v3">
            <mods:titleInfo>
               <mods:title>Gray's Inn Pension Book, 1615-16</mods:title>
            </mods:titleInfo>
            <mods:name type="corporate">
               <mods:namePart>Gray's Inn</mods:namePart>
            </mods:name>
            <mods:typeOfResource>text</mods:typeOfResource>
            <mods:genre type="formatType">Born Digital</mods:genre>
            <mods:genre type="format">born digital</mods:genre>
            <mods:genre type="primaryGenre">Record</mods:genre>
            <mods:genre type="subgenre">Archival material</mods:genre>
            <mods:genre>Performance</mods:genre>
            <mods:language>
               <mods:languageTerm type="text">English</mods:languageTerm>
            </mods:language>
            <mods:physicalDescription>
               <mods:form authority="marccategory">electronic resource</mods:form>
               <mods:internetMediaType>text/xml</mods:internetMediaType>
               <mods:digitalOrigin>born digital</mods:digitalOrigin>
            </mods:physicalDescription>
            <mods:abstract>"Surviving Pension Books date from 1568–9. William Dugdale consulted an earlier volume, now lost. His Origines Juridiciales (1666) preserves entries from 1529–30 and 1550–1 (see pp 58–9, 74; see p lxxvi for document description). Financial accounts were entered in the Pension Book to 1582–3, and thereafter in Ledger Books. The library holds microfiche of the Pension Books produced in 1976 (skipping ff 234v–5), and digital photos of PEN/1/1 (Pension Book 1), taken in 2006 when the volume was disbound for conservation.
               The standard essential publication is Reginald J. Fletcher (ed), The Pension Book of Gray’s Inn (Records of the Honourable Society)1569–1669, vol 1 (London, 1901)."</mods:abstract>
            <mods:subject>
               <mods:topic valueURI="http://id.loc.gov/authorities/subjects/sh2002012473">Theater--England--London--History--17th century
               </mods:topic>
            </mods:subject>
            <mods:subject>
               <mods:geographic valueURI="http://www.geonames.org/2643743/">London</mods:geographic>
            </mods:subject>
            <mods:subject>
               <mods:temporal point="start">1601</mods:temporal>
               <mods:temporal point="end">1700</mods:temporal>
            </mods:subject>    
            <mods:accessCondition type="use and reproduction">Use of this public-domain resource is governed by the &lt;a
               rel="license" href="http://creativecommons.org/licenses/by-nc/4.0/"
               target="blank"&gt;Creative Commons Attribution-NonCommercial 4.0 International
               License&lt;/a&gt;.</mods:accessCondition>
            <mods:recordInfo>
               <mods:recordOrigin>This MODS record was created using the Islandora XML Forms collection of Drupal modules.</mods:recordOrigin>
               <mods:languageOfCataloging>
                  <mods:languageTerm type="text">English</mods:languageTerm>
               </mods:languageOfCataloging>
               <mods:recordContentSource>Canadian Writing Research Collaboratory</mods:recordContentSource>
            </mods:recordInfo>
         </mods:mods>