<?xml version="1.0" encoding="UTF-8"?>
<?xml-model href="http://cwrc.ca/schemas/workflow.rng" type="application/xml" schematypens="http://relaxng.org/ns/structure/1.0"?>
<cwrc><workflow date="2018-08-28" userID="adminUP" time="18:33:56" timestamp="2018-08-28T18:33:56.715470+00:00" workflowID="ceww_f5808614-91e5-4c2b-8c82-d3701cd1e65b_wk_0"><activity category="published" stamp="cwrc:cre" status="c"><note>Initial ingest into the CWRC repository.</note></activity></workflow><workflow date="2018-10-23" userID="Rachel Milio" time="23:33:44" timestamp="2018-10-23T23:33:44.463348+00:00" workflowID="ceww_f5808614-91e5-4c2b-8c82-d3701cd1e65b_wk_1"><activity category="content_contribution" stamp="cwrc:cvr" status="ipr"><message><recipient userID="jakacki"/><subject>another one</subject><body>no one wanted to cough up the money for the masking apparel </body></message></activity></workflow><workflow date="2018-10-27" userID="jakacki" time="07:56:18" timestamp="2018-10-27T11:56:18.079519+00:00" workflowID="ceww_f5808614-91e5-4c2b-8c82-d3701cd1e65b_wk_2"><activity category="content_contribution" stamp="cwrc:cvr" status="ipr"/></workflow><workflow date="2018-11-04" userID="jakacki" time="15:13:28" timestamp="2018-11-04T20:13:28.939663+00:00" workflowID="ceww_f5808614-91e5-4c2b-8c82-d3701cd1e65b_wk_3"><activity category="content_contribution" stamp="cwrc:cvr" status="c"/></workflow><workflow date="2018-11-04" userID="jakacki" time="15:17:46" timestamp="2018-11-04T20:17:46.685762+00:00" workflowID="ceww_f5808614-91e5-4c2b-8c82-d3701cd1e65b_wk_4"><activity category="content_contribution" stamp="cwrc:cvr" status="c"/></workflow><workflow date="2018-11-04" userID="jakacki" time="15:18:05" timestamp="2018-11-04T20:18:05.413121+00:00" workflowID="ceww_f5808614-91e5-4c2b-8c82-d3701cd1e65b_wk_5"><activity category="content_contribution" stamp="cwrc:cvr" status="c"/></workflow><workflow date="2018-11-10" userID="jakacki" time="13:01:54" timestamp="2018-11-10T18:01:54.861737+00:00" workflowID="ceww_f5808614-91e5-4c2b-8c82-d3701cd1e65b_wk_6"><activity category="content_contribution" stamp="cwrc:cvr" status="c"/></workflow></cwrc>
